edabf/__init__.py
edabf/archivo.py
edabf/dataframe.py
edabf/dataset.py
edabf/main.py
edabf/masivo.py
edabf/table.py
edabf/data_loader/__init__.py
edabf/data_loader/eda_loader.py
edabf/data_loader/sql_operations.py
edabf/utils/__init__.py
edabf/utils/data_validation.py
edabf/utils/dataframe_operations.py
edabf/utils/excel_export.py
edabf-0.36.dist-info/METADATA
edabf-0.36.dist-info/WHEEL
edabf-0.36.dist-info/top_level.txt
edabf-0.36.dist-info/RECORD
